logmaster/__init__.py
logmaster/errors.py
logmaster/logger.py
logmaster-1.3.dist-info/LICENSE
logmaster-1.3.dist-info/METADATA
logmaster-1.3.dist-info/WHEEL
logmaster-1.3.dist-info/top_level.txt
logmaster-1.3.dist-info/RECORD
