Metadata-Version: 2.1
Name: logmaster
Version: 1.3
Summary: A simple logging library for Python
Home-page: https://github.com/W1L7dev/logmaster
Author: W1L7dev
Author-email: w1l7dev@gmail.com
License: MIT
Requires-Python: >=3.6
License-File: LICENSE
